testbook/__init__.py
testbook/_version.py
testbook/client.py
testbook/exceptions.py
testbook/reference.py
testbook/testbook.py
testbook/testbooknode.py
testbook/translators.py
testbook/utils.py
nteract_testbook-0.1.3.dist-info/LICENSE
nteract_testbook-0.1.3.dist-info/METADATA
nteract_testbook-0.1.3.dist-info/WHEEL
nteract_testbook-0.1.3.dist-info/top_level.txt
nteract_testbook-0.1.3.dist-info/RECORD
