Metadata-Version: 2.1
Name: nteract-testbook
Version: 0.1.3
Summary: A unit testing framework for Jupyter Notebooks
Home-page: https://github.com/nteract/testbook
Author: nteract contributors
Author-email: nteract@googlegroups.com
License: BSD
Project-URL: Documentation, https://test-book.readthedocs.io
Project-URL: Funding, https://nteract.io
Project-URL: Source, https://github.com/nteract/testbook/
Project-URL: Tracker, https://github.com/nteract/testbook/issues
Keywords: jupyter mapreduce nteract pipeline notebook
Platform: UNKNOWN
Classifier: Intended Audience :: Developers
Classifier: License :: OSI Approved :: BSD License
Classifier: Programming Language :: Python
Classifier: Programming Language :: Python :: 3
Classifier: Programming Language :: Python :: 3.6
Classifier: Programming Language :: Python :: 3.7
Classifier: Programming Language :: Python :: 3.8
Requires-Python: >=3.5
Requires-Dist: nbformat (>=5.0.4)
Requires-Dist: nbclient (>=0.4.0)
Provides-Extra: dev
Requires-Dist: codecov ; extra == 'dev'
Requires-Dist: coverage ; extra == 'dev'
Requires-Dist: ipython ; extra == 'dev'
Requires-Dist: ipykernel ; extra == 'dev'
Requires-Dist: ipywidgets ; extra == 'dev'
Requires-Dist: pytest (>=4.1) ; extra == 'dev'
Requires-Dist: pytest-cov (>=2.6.1) ; extra == 'dev'
Requires-Dist: check-manifest ; extra == 'dev'
Requires-Dist: flake8 ; extra == 'dev'
Requires-Dist: tox ; extra == 'dev'
Requires-Dist: bumpversion ; extra == 'dev'
Requires-Dist: xmltodict ; extra == 'dev'
Requires-Dist: pip (>=18.1) ; extra == 'dev'
Requires-Dist: wheel (>=0.31.0) ; extra == 'dev'
Requires-Dist: setuptools (>=38.6.0) ; extra == 'dev'
Requires-Dist: twine (>=1.11.0) ; extra == 'dev'
Requires-Dist: black ; (python_version >= "3.6") and extra == 'dev'
Provides-Extra: sphinx
Requires-Dist: Sphinx (>=1.7) ; extra == 'sphinx'
Requires-Dist: sphinx-book-theme ; extra == 'sphinx'
Requires-Dist: mock ; extra == 'sphinx'
Requires-Dist: moto ; extra == 'sphinx'
Requires-Dist: myst-parser ; extra == 'sphinx'
Requires-Dist: myst-nb ; extra == 'sphinx'
Provides-Extra: test
Requires-Dist: codecov ; extra == 'test'
Requires-Dist: coverage ; extra == 'test'
Requires-Dist: ipython ; extra == 'test'
Requires-Dist: ipykernel ; extra == 'test'
Requires-Dist: ipywidgets ; extra == 'test'
Requires-Dist: pytest (>=4.1) ; extra == 'test'
Requires-Dist: pytest-cov (>=2.6.1) ; extra == 'test'
Requires-Dist: check-manifest ; extra == 'test'
Requires-Dist: flake8 ; extra == 'test'
Requires-Dist: tox ; extra == 'test'
Requires-Dist: bumpversion ; extra == 'test'
Requires-Dist: xmltodict ; extra == 'test'
Requires-Dist: pip (>=18.1) ; extra == 'test'
Requires-Dist: wheel (>=0.31.0) ; extra == 'test'
Requires-Dist: setuptools (>=38.6.0) ; extra == 'test'
Requires-Dist: twine (>=1.11.0) ; extra == 'test'
Requires-Dist: black ; (python_version >= "3.6") and extra == 'test'
